mrina-0.3.0.dist-info/RECORD
mrina-0.3.0.dist-info/METADATA
mrina-0.3.0.dist-info/top_level.txt
mrina-0.3.0.dist-info/WHEEL
mrina/__init__.py
mrina/recover.py
mrina/solver_omp.c
mrina/correlation.py
mrina/plot_corr.py
mrina/vtktoimg.py
mrina/plot_mse.py
mrina/solver_l1_norm.py
mrina/save_imgs.py
mrina/maps.py
mrina/solver_nuclear_norm.py
mrina/solver_omp.cpython-38-x86_64-linux-gnu.so
mrina/gen_samples.py
mrina/mri_utils.py
