Metadata-Version: 2.1
Name: mrina
Version: 0.3.0
Summary: Library for MRI noise analysis
Home-page: https://mrina.readthedocs.io/
Author: Lauren Partin, Daniele Schiavazzi, Carlos Sing-Long
Author-email: example@email.com
License: MIT
Platform: UNKNOWN
Classifier: Intended Audience :: Developers
Classifier: License :: OSI Approved :: MIT License
Classifier: Programming Language :: Python
Classifier: Programming Language :: Python :: 3.7
Classifier: Programming Language :: Python :: 3.8
Classifier: Programming Language :: Python :: 3.9
Classifier: Programming Language :: Python :: 3.10
Classifier: Operating System :: OS Independent
Requires-Dist: numpy
